EnORM/__init__.py
EnORM/column.py
EnORM/constants.py
EnORM/custom_types.py
EnORM/db_engine.py
EnORM/db_session.py
EnORM/exceptions.py
EnORM/fkey.py
EnORM/functions.py
EnORM/model.py
EnORM/pool.py
EnORM/query.py
EnORM/subquery.py
EnORM/backends/__init__.py
EnORM/backends/mysql.py
EnORM/backends/oracle.py
EnORM/backends/postgresql.py
EnORM/backends/sql_server.py
enorm-1.2.2.dist-info/licenses/LICENSE
enorm-1.2.2.dist-info/METADATA
enorm-1.2.2.dist-info/WHEEL
enorm-1.2.2.dist-info/top_level.txt
enorm-1.2.2.dist-info/RECORD
