Metadata-Version: 2.4
Name: EnORM
Version: 1.2.2
Summary: EnORM—EnDATA Object Relational Mapper.
Author-email: Nima Bavari <nima.bavari@gmail.com>
Project-URL: Homepage, https://github.com/NimaBavari/EnORM
Project-URL: Bug Tracker, https://github.com/NimaBavari/EnORM/issues
Classifier: Programming Language :: Python :: 3
Classifier: License :: OSI Approved :: MIT License
Classifier: Operating System :: OS Independent
Requires-Python: >=3.10
License-File: LICENSE
Requires-Dist: macaddress>=2.0.2
Requires-Dist: pyodbc>=5.2.0
Requires-Dist: shapely>=2.0.6
Dynamic: license-file
